odoo10_addon_stock_valued_picking_report_triple_discount-10.0.1.0.0.99.dev3-nspkg.pth
odoo/addons/stock_valued_picking_report_triple_discount/README.rst
odoo/addons/stock_valued_picking_report_triple_discount/__init__.py
odoo/addons/stock_valued_picking_report_triple_discount/__manifest__.py
odoo/addons/stock_valued_picking_report_triple_discount/i18n/es.po
odoo/addons/stock_valued_picking_report_triple_discount/i18n/stock_valued_picking_report_triple_discount.pot
odoo/addons/stock_valued_picking_report_triple_discount/models/__init__.py
odoo/addons/stock_valued_picking_report_triple_discount/models/stock_pack_operation.py
odoo/addons/stock_valued_picking_report_triple_discount/report/stock_valued_picking_report_triple_discount.xml
odoo/addons/stock_valued_picking_report_triple_discount/static/description/icon.png
odoo/addons/stock_valued_picking_report_triple_discount/tests/__init__.py
odoo/addons/stock_valued_picking_report_triple_discount/tests/test_stock_picking_valued_report_triple_discount.py
odoo10_addon_stock_valued_picking_report_triple_discount-10.0.1.0.0.99.dev3.dist-info/METADATA
odoo10_addon_stock_valued_picking_report_triple_discount-10.0.1.0.0.99.dev3.dist-info/WHEEL
odoo10_addon_stock_valued_picking_report_triple_discount-10.0.1.0.0.99.dev3.dist-info/namespace_packages.txt
odoo10_addon_stock_valued_picking_report_triple_discount-10.0.1.0.0.99.dev3.dist-info/top_level.txt
odoo10_addon_stock_valued_picking_report_triple_discount-10.0.1.0.0.99.dev3.dist-info/RECORD
