Metadata-Version: 2.1
Name: odoo10-addon-stock-valued-picking-report-triple-discount
Version: 10.0.1.0.0.99.dev3
Summary: Adding Triple Discount on Valued Picking Report
Home-page: https://github.com/OCA/stock-logistics-reporting
Author: Tecnativa, Odoo Community Association (OCA)
Author-email: support@odoo-community.org
License: AGPL-3
Platform: UNKNOWN
Classifier: Programming Language :: Python
Classifier: Framework :: Odoo
Classifier: License :: OSI Approved :: GNU Affero General Public License v3
Requires-Python: ~=2.7
Requires-Dist: odoo10-addon-sale-triple-discount
Requires-Dist: odoo10-addon-stock-valued-picking-report
Requires-Dist: odoo (<10.1dev,>=10.0)
